netds/__about__.py
netds/__init__.py
netds/netsi_data.py
netds/.ipynb_checkpoints/netsi_data-checkpoint.py
netds-0.1.dist-info/METADATA
netds-0.1.dist-info/WHEEL
netds-0.1.dist-info/licenses/LICENSE.txt
netds-0.1.dist-info/RECORD
