Metadata-Version: 2.3
Name: netds
Version: 0.1
Project-URL: Documentation, https://github.com/liu-yi-xuan/netdata#readme
Project-URL: Issues, https://github.com/liu-yi-xuan/netdata/issues
Project-URL: Source, https://github.com/liu-yi-xuan/netdata
Author-email: liu-yi-xuan <53630521+liu-yi-xuan@users.noreply.github.com>
License-Expression: MIT
License-File: LICENSE.txt
Classifier: Development Status :: 4 - Beta
Classifier: Programming Language :: Python
Classifier: Programming Language :: Python :: 3.8
Classifier: Programming Language :: Python :: 3.9
Classifier: Programming Language :: Python :: 3.10
Classifier: Programming Language :: Python :: 3.11
Classifier: Programming Language :: Python :: 3.12
Requires-Python: >=3.9
